MANIFEST.in
README.md
setup.cfg
setup.py
pyramid_mongoengine/__init__.py
pyramid_mongoengine/utils.py
pyramid_mongoengine.egg-info/PKG-INFO
pyramid_mongoengine.egg-info/SOURCES.txt
pyramid_mongoengine.egg-info/dependency_links.txt
pyramid_mongoengine.egg-info/not-zip-safe
pyramid_mongoengine.egg-info/requires.txt
pyramid_mongoengine.egg-info/top_level.txt
pyramid_mongoengine/tests/__init__.py
pyramid_mongoengine/tests/test_app.py
pyramid_mongoengine/tests/apptest/__init__.py