Metadata-Version: 1.0
Name: pyramid-mongoengine
Version: 0.0.1
Summary: Mongoengine Pyramid extension based in flask-mongoengine
Home-page: https://github.com/marioidival/pyramid_mongoengine
Author: Mario Idival
Author-email: marioidival@gmail.com
License: MIT
Keywords: pyramid mongoengine python os opensource
Platform: UNKNOWN
